setup.py
godb/__init__.py
godb.egg-info/PKG-INFO
godb.egg-info/SOURCES.txt
godb.egg-info/dependency_links.txt
godb.egg-info/requires.txt
godb.egg-info/top_level.txt
godb/config/__init__.py
godb/config/settings.py
godb/config/version.py
godb/get_and_parse_data/__init__.py
godb/get_and_parse_data/obo_to_df.py
godb/messy_df_to_user_data/__init__.py
godb/messy_df_to_user_data/getters.py